{
  "timestamp": "2025-10-17T15:24:14.527+09:00",
  "scenarioName": "48歳女性・しびれ",
  "passed": false,
  "summary": {
    "cDiagnosis": {
      "questionCount": 38,
      "diseaseCount": 10,
      "executionTimeMs": 78515
    },
    "askman": {
      "questionCount": 36,
      "diseaseCount": 10,
      "executionTimeMs": 94310
    }
  },
  "diseases": {
    "cDiagnosis": [
      {
        "id": "頚椎症",
        "name": "頚椎症",
        "section": "related"
      },
      {
        "id": "てんかん",
        "name": "てんかん",
        "section": "related"
      },
      {
        "id": "脊髄損傷急性期",
        "name": "脊髄損傷急性期",
        "section": "related"
      },
      {
        "id": "神経障害性疼痛",
        "name": "神経障害性疼痛",
        "section": "related"
      },
      {
        "id": "更年期障害",
        "name": "更年期障害",
        "section": "related"
      },
      {
        "id": "梨状筋症候群",
        "name": "梨状筋症候群",
        "section": "related"
      },
      {
        "id": "変形性腰椎症",
        "name": "変形性腰椎症",
        "section": "related"
      },
      {
        "id": "頚髄損傷",
        "name": "頚髄損傷",
        "section": "related"
      },
      {
        "id": "視神経脊髄炎",
        "name": "視神経脊髄炎",
        "label": "指定難病",
        "section": "easily-missed"
      },
      {
        "id": "多発性硬化症(MS)",
        "name": "多発性硬化症(MS)",
        "label": "指定難病",
        "section": "easily-missed"
      }
    ],
    "askman": [
      {
        "id": "てんかん",
        "name": "てんかん",
        "section": "related"
      },
      {
        "id": "頚椎症",
        "name": "頚椎症",
        "section": "related"
      },
      {
        "id": "更年期障害",
        "name": "更年期障害",
        "section": "related"
      },
      {
        "id": "甲状腺機能低下症",
        "name": "甲状腺機能低下症",
        "section": "related"
      },
      {
        "id": "レストレスレッグス症候群(むずむず脚症候群)",
        "name": "レストレスレッグス症候群(むずむず脚症候群)",
        "section": "related"
      },
      {
        "id": "高尿酸血症",
        "name": "高尿酸血症",
        "section": "related"
      },
      {
        "id": "線維筋痛症",
        "name": "線維筋痛症",
        "section": "related"
      },
      {
        "id": "関節リウマチ",
        "name": "関節リウマチ",
        "label": "指定難病と関連あり",
        "section": "related"
      },
      {
        "id": "多発性硬化症(MS)",
        "name": "多発性硬化症(MS)",
        "label": "指定難病",
        "section": "easily-missed"
      },
      {
        "id": "一過性脳虚血発作",
        "name": "一過性脳虚血発作",
        "section": "easily-missed"
      }
    ]
  },
  "questionLogs": {
    "cDiagnosis": [
      {
        "questionNumber": 1,
        "url": "https://staging.ubie.app/qa/relationship",
        "questionText": "誰の症状について調べますか？",
        "availableOptions": [
          "自分",
          "家族",
          "その他"
        ],
        "selectedOption": "自分",
        "timestamp": 1760682170386
      },
      {
        "questionNumber": 2,
        "url": "https://staging.ubie.app/qa/age",
        "questionText": "年齢を教えてください",
        "availableOptions": [],
        "selectedOption": "48歳",
        "timestamp": 1760682170638
      },
      {
        "questionNumber": 3,
        "url": "https://staging.ubie.app/qa/sex",
        "questionText": "性別を教えてください",
        "availableOptions": [
          "男性",
          "女性"
        ],
        "selectedOption": "女性",
        "timestamp": 1760682170789
      },
      {
        "questionNumber": 4,
        "url": "https://staging.ubie.app/qa/height",
        "questionText": "身長を教えてください",
        "availableOptions": [
          "80-200cm"
        ],
        "selectedOption": "143cm",
        "timestamp": 1760682172046
      },
      {
        "questionNumber": 5,
        "url": "https://staging.ubie.app/qa/weight",
        "questionText": "体重を教えてください",
        "availableOptions": [
          "10-130kg"
        ],
        "selectedOption": "36kg",
        "timestamp": 1760682173124
      },
      {
        "questionNumber": 6,
        "url": "https://staging.ubie.app/qa/question/main-complaint",
        "questionText": "現在、最も気になる症状を教えてください。",
        "availableOptions": [
          "体の片側に感覚障害がある",
          "更年期障害だと思う",
          "開口障害がある",
          "意識障害がある",
          "言語障害がある",
          "目の調節障害がある",
          "しびれがある",
          "肌にしびれを感じる",
          "右手の指のしびれ"
        ],
        "selectedOption": "体の片側に感覚障害がある",
        "timestamp": 1760682174671
      },
      {
        "questionNumber": 7,
        "url": "https://staging.ubie.app/qa/question/main-complaint/confirm",
        "questionText": "【体の片側に感覚障害がある】に関する質問に進みます",
        "availableOptions": [],
        "selectedOption": "次へ進む",
        "timestamp": 1760682174958
      },
      {
        "questionNumber": 8,
        "url": "https://staging.ubie.app/qa/question/question-16095",
        "questionText": "【妊娠・授乳】の状況で、当てはまるものを【すべて】選んでください。",
        "availableOptions": [
          "現在、妊娠している",
          "確定していないが、妊娠しているかもしれない",
          "現在、授乳中である",
          "この中に該当なし",
          "回答をとばす"
        ],
        "selectedOption": "現在、授乳中である",
        "timestamp": 1760682176129
      },
      {
        "questionNumber": 9,
        "url": "https://staging.ubie.app/qa/question/question-10692",
        "questionText": "つぎのような症状はありますか？当てはまるものを全て選んでください",
        "availableOptions": [
          "頭がボーっとする、すっきりしない",
          "頭痛がある・頭が重い",
          "体温が37.5℃以上",
          "ろれつが回らない",
          "息苦しさを感じる",
          "皮ふに何らかの異常がある",
          "手足などに力の入らない部分がある",
          "この中に該当なし",
          "回答をとばす"
        ],
        "selectedOption": "体温が37.5℃以上",
        "timestamp": 1760682178325
      },
      {
        "questionNumber": 10,
        "url": "https://staging.ubie.app/qa/question/question-8114",
        "questionText": "今回の【体の片側に感覚障害がある】はどのくらい前からですか？",
        "availableOptions": [
          "回答をとばす"
        ],
        "selectedOption": "回答をとばす",
        "timestamp": 1760682180318
      },
      {
        "questionNumber": 11,
        "url": "https://staging.ubie.app/qa/question/question-8276",
        "questionText": "【体の片側に感覚障害がある】の現れ方について、一番近いものを以下から選んでください。",
        "availableOptions": [
          "全く前ぶれのない突然の発症だった",
          "速やかに悪化した",
          "徐々に症状が現れた",
          "回答をとばす"
        ],
        "selectedOption": "全く前ぶれのない突然の発症だった",
        "timestamp": 1760682181603
      },
      {
        "questionNumber": 12,
        "url": "https://staging.ubie.app/qa/question/question-10537",
        "questionText": "これまでに同じような【体の片側に感覚障害がある】を経験したことはありますか？一番近いものを以下から選んでください。",
        "availableOptions": [
          "初めての症状である",
          "これまでに1回以上同じような症状があった",
          "年に数回程度は同じような症状がある",
          "月に数回程度は同じような症状がある",
          "ほぼ毎日同じような症状がある",
          "回答をとばす"
        ],
        "selectedOption": "初めての症状である",
        "timestamp": 1760682182931
      },
      {
        "questionNumber": 13,
        "url": "https://staging.ubie.app/qa/question/question-9892",
        "questionText": "【体の片側に感覚障害がある】の場所を教えてください",
        "availableOptions": [
          "手の指がしびれる",
          "手足以外のカラダにしびれがある",
          "顔や口周囲のしびれがある",
          "腕がしびれる",
          "お尻や腰回りにしびれがある",
          "足の付け根から足指のどこかにしびれがある",
          "この中に該当なし",
          "回答をとばす"
        ],
        "selectedOption": "手足以外のカラダにしびれがある",
        "timestamp": 1760682184167
      },
      {
        "questionNumber": 14,
        "url": "https://staging.ubie.app/qa/question/question-9994",
        "questionText": "【体の片側に感覚障害がある】の程度について、一番近いものを以下から選んでください。",
        "availableOptions": [
          "違和感がある",
          "やや耐えがたい",
          "とても耐えられない",
          "日常生活が困難である",
          "回答をとばす"
        ],
        "selectedOption": "回答をとばす",
        "timestamp": 1760682186036
      },
      {
        "questionNumber": 15,
        "url": "https://staging.ubie.app/qa/question/question-8326",
        "questionText": "【体の片側に感覚障害がある】はどのくらい続いていますか？",
        "availableOptions": [
          "15分以内",
          "1時間以内",
          "1時間以上続いている",
          "回答をとばす"
        ],
        "selectedOption": "1時間以内",
        "timestamp": 1760682187092
      },
      {
        "questionNumber": 16,
        "url": "https://staging.ubie.app/qa/question/question-7785",
        "questionText": "【体の片側に感覚障害がある】のはじまりから現在までの変化として、一番近いものはどれですか？",
        "availableOptions": [
          "悪化している",
          "改善も悪化もしていない",
          "改善したがまだ残っている",
          "改善し、現在はない",
          "回答をとばす"
        ],
        "selectedOption": "改善したがまだ残っている",
        "timestamp": 1760682189018
      },
      {
        "questionNumber": 17,
        "url": "https://staging.ubie.app/qa/question/question-9406",
        "questionText": "【体の片側に感覚障害がある】はどのような様子・状態ですか",
        "availableOptions": [
          "バランス感覚がおかしく、上手く立っていられない",
          "触ってないのにジンジン、ピリピリとしびれる感じがする",
          "この中に該当なし",
          "回答をとばす"
        ],
        "selectedOption": "回答をとばす",
        "timestamp": 1760682190352
      },
      {
        "questionNumber": 18,
        "url": "https://staging.ubie.app/qa/question/question-13636",
        "questionText": "一番最近の血液検査で、貧血を指摘されましたか？",
        "availableOptions": [
          "はい",
          "いいえ",
          "わからない",
          "回答をとばす"
        ],
        "selectedOption": "はい",
        "timestamp": 1760682191520
      },
      {
        "questionNumber": 19,
        "url": "https://staging.ubie.app/qa/question/question-15705_health_history_general",
        "questionText": "これまでにかかったことがある病気を【全て】選んでください",
        "availableOptions": [
          "気管支・肺の病気気管支喘息、慢性閉塞性肺疾患（COPD）、肺線維症・間質性肺炎",
          "リウマチ・膠原病関節リウマチ、全身性エリテマトーデス（SLE）、強皮症、多発性筋炎・皮膚筋炎、シェーグレン症候群",
          "アレルギー関連の病気アトピー性皮膚炎、気管支喘息、鼻茸（鼻ポリープ）、結節性痒疹、慢性閉塞性肺疾患（COPD）、慢性蕁麻疹、慢性副鼻腔炎、アレルギー性鼻炎、食物アレルギー",
          "生活習慣病・貧血糖尿病、脂質異常症、脂肪肝、貧血、高血圧",
          "皮ふの病気乾癬、アトピー性皮膚炎、慢性蕁麻疹、結節性痒疹",
          "腎臓の病気慢性腎臓病・慢性腎不全",
          "胃腸の病気潰瘍性大腸炎、胃食道逆流症（GERD/逆流性食道炎）、クローン病、機能性ディスペプシア、便秘症、胃・十二指腸潰瘍",
          "心臓の病気心不全、心筋梗塞・不安定狭心症、不整脈",
          "精神科・心療内科の病気うつ病、注意欠如多動症（ADHD）、統合失調症、双極性感情障害（躁うつ病）",
          "がん肺がん、乳がん、食道がん、胃がん、大腸がん、子宮頸がん、膵臓がん、前立腺がん、肝臓がん、皮膚がん",
          "この中に該当なし",
          "回答をとばす"
        ],
        "selectedOption": "回答をとばす",
        "timestamp": 1760682193013
      },
      {
        "questionNumber": 20,
        "url": "https://staging.ubie.app/qa/question/question-15656",
        "questionText": "以下の【アレルギーに関連する病気】をお持ちですか？当てはまるものを【全て】選んでください。",
        "availableOptions": [
          "アトピー性皮膚炎",
          "気管支喘息",
          "鼻茸（鼻ポリープ）",
          "結節性痒疹",
          "慢性蕁麻疹（じんましん）",
          "COPD（慢性閉塞性肺疾患）",
          "この中に該当なし",
          "回答をとばす"
        ],
        "selectedOption": "結節性痒疹",
        "timestamp": 1760682194387
      },
      {
        "questionNumber": 21,
        "url": "https://staging.ubie.app/qa/question/question-16275",
        "questionText": "以下の【生活習慣病などの病気】にかかったことがありますか？当てはまるものを【全て】選んでください。",
        "availableOptions": [
          "高血圧症",
          "脂質異常症",
          "糖尿病",
          "慢性腎臓病・慢性腎不全",
          "狭心症・心筋梗塞",
          "高尿酸血症",
          "痛風",
          "睡眠時無呼吸症候群",
          "脂肪肝",
          "脳梗塞",
          "一過性脳虚血発作",
          "変形性膝関節症",
          "変形性股関節症",
          "変形性脊椎症",
          "肥満低換気症候群",
          "この中に該当なし",
          "回答をとばす"
        ],
        "selectedOption": "変形性脊椎症",
        "timestamp": 1760682196526
      },
      {
        "questionNumber": 22,
        "url": "https://staging.ubie.app/qa/question/question-19745",
        "questionText": "これまで、【体重を減らす方法】について医師に相談したことがありますか？",
        "availableOptions": [
          "相談したことがある",
          "相談したいが、実際にしたことはない",
          "相談したいと思ったこともない",
          "覚えていない",
          "回答をとばす"
        ],
        "selectedOption": "相談したいが、実際にしたことはない",
        "timestamp": 1760682198581
      },
      {
        "questionNumber": 23,
        "url": "https://staging.ubie.app/qa/question/question-19012",
        "questionText": "現在、医療スタッフによる【食事指導】や【運動指導】を、継続して受けていますか？最も近いものを【1つ】お選びください。",
        "availableOptions": [
          "最近指導を受けたばかり",
          "1ヶ月ほど継続している",
          "2ヶ月から3ヶ月ほど継続している",
          "4ヶ月から5ヶ月ほど継続している",
          "6ヶ月以上継続している",
          "指導を受けたが、やめてしまった",
          "指導を受けたことはない",
          "回答をとばす"
        ],
        "selectedOption": "1ヶ月ほど継続している",
        "timestamp": 1760682200124
      },
      {
        "questionNumber": 24,
        "url": "https://staging.ubie.app/qa/question/question-16347",
        "questionText": "ここ1年で、生理が遅れる、あるいは早まっているということがありますか？",
        "availableOptions": [
          "はい",
          "いいえ",
          "わからない",
          "回答をとばす"
        ],
        "selectedOption": "回答をとばす",
        "timestamp": 1760682201449
      },
      {
        "questionNumber": 25,
        "url": "https://staging.ubie.app/qa/question/question-15455",
        "questionText": "医師に腎臓（じんぞう）の機能の低下を指摘されたことがありますか？",
        "availableOptions": [
          "ある（慢性腎臓病と診断済み）",
          "ある（慢性腎臓病と診断されていない）",
          "ない",
          "ないが、健康診断の血液検査（クレアチニン、eGFR）や尿検査で異常を指摘されている",
          "回答をとばす"
        ],
        "selectedOption": "ないが、健康診断の血液検査（クレアチニン、eGFR）や尿検査で異常を指摘されている",
        "timestamp": 1760682202545
      },
      {
        "questionNumber": 26,
        "url": "https://staging.ubie.app/qa/question/symptoms-309-731-993",
        "questionText": "次のような症状などはありますか？",
        "availableOptions": [
          "視界の一部が見えなくなった",
          "最近目が見えにくくなった",
          "目の痛みがある",
          "この中に該当なし",
          "回答をとばす"
        ],
        "selectedOption": "視界の一部が見えなくなった",
        "timestamp": 1760682204084
      },
      {
        "questionNumber": 27,
        "url": "https://staging.ubie.app/qa/question/symptoms-152-2827",
        "questionText": "次のような症状などはありますか？",
        "availableOptions": [
          "しゃっくりが止まらない、または頻繁に出る",
          "吐き気・嘔吐がある",
          "この中に該当なし",
          "回答をとばす"
        ],
        "selectedOption": "この中に該当なし",
        "timestamp": 1760682206269
      },
      {
        "questionNumber": 28,
        "url": "https://staging.ubie.app/qa/question/symptom-1460",
        "questionText": "安静にしていると痛みを感じないが、立ち上がる、歩く、階段をのぼる等の動作をすることで痛みが出て来ますか？",
        "availableOptions": [
          "はい",
          "いいえ",
          "わからない",
          "回答をとばす"
        ],
        "selectedOption": "回答をとばす",
        "timestamp": 1760682208292
      },
      {
        "questionNumber": 29,
        "url": "https://staging.ubie.app/qa/question/symptom-1563",
        "questionText": "首の痛みやこわばりがありますか？",
        "availableOptions": [
          "はい",
          "いいえ",
          "わからない",
          "回答をとばす"
        ],
        "selectedOption": "わからない",
        "timestamp": 1760682209786
      },
      {
        "questionNumber": 30,
        "url": "https://staging.ubie.app/qa/question/symptom-66",
        "questionText": "皮ふの感覚がにぶく、痛みなどが感じにくいですか？",
        "availableOptions": [
          "はい",
          "いいえ",
          "わからない",
          "回答をとばす"
        ],
        "selectedOption": "はい",
        "timestamp": 1760682211286
      },
      {
        "questionNumber": 31,
        "url": "https://staging.ubie.app/qa/question/continue-symptom-answer",
        "questionText": "ここまでの回答でおおよその結果を確認できます",
        "availableOptions": [
          "ここまでの回答で結果を見る",
          "このまま回答を続ける"
        ],
        "selectedOption": "ここまでの回答で結果を見る",
        "timestamp": 1760682212887
      },
      {
        "questionNumber": 32,
        "url": "https://staging.ubie.app/qa/question/question-predicted-disease",
        "questionText": "この中でかかったことがある病気をすべて選んでください",
        "availableOptions": [
          "頚椎症",
          "てんかん",
          "脊髄損傷急性期",
          "神経障害性疼痛",
          "更年期障害",
          "梨状筋症候群",
          "変形性腰椎症",
          "頚髄損傷",
          "視神経脊髄炎",
          "多発性硬化症(MS)",
          "この中に該当なし",
          "回答をとばす"
        ],
        "selectedOption": "更年期障害",
        "timestamp": 1760682217852
      },
      {
        "questionNumber": 33,
        "url": "https://staging.ubie.app/qa/question/disease-under-treatment",
        "questionText": "この中に治療中、またはお薬を飲んでいる病気はありますか？",
        "availableOptions": [
          "結節性痒疹(けっせつせいようしん)",
          "変形性脊椎症",
          "更年期障害",
          "この中に該当なし"
        ],
        "selectedOption": "更年期障害",
        "timestamp": 1760682219988
      },
      {
        "questionNumber": 34,
        "url": "https://staging.ubie.app/qa/question/diagnosed-poorly-controlled-disease-206-question-19750",
        "questionText": "次のうち、更年期の症状に対して【1ヶ月以上使用している】お薬やサプリメントはありますか？当てはまるものを【全て】お選びください。",
        "availableOptions": [
          "女性ホルモン補充療法",
          "漢方薬",
          "抗うつ薬、抗不安薬",
          "サプリメント、市販薬",
          "この中に該当なし"
        ],
        "selectedOption": "漢方薬",
        "timestamp": 1760682222111
      },
      {
        "questionNumber": 35,
        "url": "https://staging.ubie.app/qa/question/diagnosed-poorly-controlled-disease-206-question-19749",
        "questionText": "【最近1ヶ月間で】次のような症状はありましたか？当てはまるものを【全て】お選びください。",
        "availableOptions": [
          "突然、顔や上半身が熱くなる（ほてり、のぼせ）",
          "ほてり、のぼせと一緒に動悸がする",
          "汗をかいた後に寒気を感じる",
          "夜間の発汗で目が覚める",
          "この中に該当なし"
        ],
        "selectedOption": "この中に該当なし",
        "timestamp": 1760682224154
      },
      {
        "questionNumber": 36,
        "url": "https://staging.ubie.app/qa/question/diagnosed-poorly-controlled-disease-206-question-19748",
        "questionText": "次のうち、これまでにかかったことがある病気はありますか？当てはまるものを【全て】お選びください。",
        "availableOptions": [
          "子宮筋腫",
          "子宮体癌",
          "乳癌",
          "血栓症（脳梗塞、心筋梗塞、深部静脈血栓症など）",
          "片頭痛",
          "糖尿病",
          "この中に該当なし",
          "回答をとばす"
        ],
        "selectedOption": "乳癌",
        "timestamp": 1760682226212
      },
      {
        "questionNumber": 37,
        "url": "https://staging.ubie.app/qa/question/diagnosed-poorly-controlled-disease-206-visit-status",
        "questionText": "【更年期障害】の治療のため、病院に通っていますか？",
        "availableOptions": [
          "病院に通っている",
          "病院に通っていない",
          "回答をとばす"
        ],
        "selectedOption": "病院に通っていない",
        "timestamp": 1760682228175
      },
      {
        "questionNumber": 38,
        "url": "https://staging.ubie.app/qa/question/symptom-care-needs",
        "questionText": "今回、【体の片側に感覚障害がある】についてどのような対応をしたいですか？",
        "availableOptions": [
          "市販薬で対処したい",
          "医師に診てもらいたい",
          "症状に関する病気を詳しく知りたい",
          "該当するものがない",
          "回答をとばす"
        ],
        "selectedOption": "市販薬で対処したい",
        "timestamp": 1760682230170
      }
    ],
    "askman": [
      {
        "questionNumber": 1,
        "url": "https://staging.ubie.app/qa/question/person",
        "questionText": "誰の症状について調べますか？",
        "availableOptions": [
          "自分",
          "家族",
          "その他"
        ],
        "selectedOption": "自分",
        "timestamp": 1760682170520
      },
      {
        "questionNumber": 2,
        "url": "https://staging.ubie.app/qa/question/age",
        "questionText": "年齢を教えてください",
        "availableOptions": [],
        "selectedOption": "48歳",
        "timestamp": 1760682171424
      },
      {
        "questionNumber": 3,
        "url": "https://staging.ubie.app/qa/question/sex",
        "questionText": "性別を教えてください",
        "availableOptions": [
          "男性",
          "女性"
        ],
        "selectedOption": "女性",
        "timestamp": 1760682172310
      },
      {
        "questionNumber": 4,
        "url": "https://staging.ubie.app/qa/question/height",
        "questionText": "身長を教えてください",
        "availableOptions": [
          "80-200cm"
        ],
        "selectedOption": "143cm",
        "timestamp": 1760682174296
      },
      {
        "questionNumber": 5,
        "url": "https://staging.ubie.app/qa/question/weight",
        "questionText": "体重を教えてください",
        "availableOptions": [
          "10-130kg"
        ],
        "selectedOption": "36kg",
        "timestamp": 1760682177184
      },
      {
        "questionNumber": 6,
        "url": "https://staging.ubie.app/qa/question/main-symptom",
        "questionText": "現在、最も気になる症状を教えてください。",
        "availableOptions": [
          "体の片側に感覚障害がある",
          "更年期障害だと思う",
          "開口障害がある",
          "意識障害がある",
          "言語障害がある",
          "目の調節障害がある",
          "しびれがある",
          "肌にしびれを感じる",
          "右手の指のしびれ"
        ],
        "selectedOption": "体の片側に感覚障害がある",
        "timestamp": 1760682178905
      },
      {
        "questionNumber": 7,
        "url": "https://staging.ubie.app/qa/question/main-symptom/confirm",
        "questionText": "【体の片側に感覚障害がある】に関する質問に進みます",
        "availableOptions": [],
        "selectedOption": "次へ進む",
        "timestamp": 1760682179473
      },
      {
        "questionNumber": 8,
        "url": "https://staging.ubie.app/qa/question/question-16123",
        "questionText": "【これまでに】タバコ（電子タバコ等も含む）を吸ったことがありますか？",
        "availableOptions": [
          "はい",
          "いいえ",
          "わからない",
          "回答をとばす"
        ],
        "selectedOption": "回答をとばす",
        "timestamp": 1760682183012
      },
      {
        "questionNumber": 9,
        "url": "https://staging.ubie.app/qa/question/question-16095",
        "questionText": "【妊娠・授乳】の状況で、当てはまるものを【すべて】選んでください。",
        "availableOptions": [
          "現在、妊娠している",
          "確定していないが、妊娠しているかもしれない",
          "現在、授乳中である",
          "この中に該当なし",
          "回答をとばす"
        ],
        "selectedOption": "現在、授乳中である",
        "timestamp": 1760682184393
      },
      {
        "questionNumber": 10,
        "url": "https://staging.ubie.app/qa/question/question-10692",
        "questionText": "つぎのような症状はありますか？当てはまるものを全て選んでください",
        "availableOptions": [
          "頭がボーっとする、すっきりしない",
          "頭痛がある・頭が重い",
          "体温が37.5℃以上",
          "ろれつが回らない",
          "息苦しさを感じる",
          "皮ふに何らかの異常がある",
          "手足などに力の入らない部分がある",
          "この中に該当なし",
          "回答をとばす"
        ],
        "selectedOption": "体温が37.5℃以上",
        "timestamp": 1760682187787
      },
      {
        "questionNumber": 11,
        "url": "https://staging.ubie.app/qa/question/question-8114",
        "questionText": "今回の【体の片側に感覚障害がある】はどのくらい前からですか？",
        "availableOptions": [
          "回答をとばす"
        ],
        "selectedOption": "回答をとばす",
        "timestamp": 1760682190505
      },
      {
        "questionNumber": 12,
        "url": "https://staging.ubie.app/qa/question/question-8276",
        "questionText": "【体の片側に感覚障害がある】の現れ方について、一番近いものを以下から選んでください。",
        "availableOptions": [
          "全く前ぶれのない突然の発症だった",
          "速やかに悪化した",
          "徐々に症状が現れた",
          "回答をとばす"
        ],
        "selectedOption": "全く前ぶれのない突然の発症だった",
        "timestamp": 1760682193436
      },
      {
        "questionNumber": 13,
        "url": "https://staging.ubie.app/qa/question/question-10537",
        "questionText": "これまでに同じような【体の片側に感覚障害がある】を経験したことはありますか？一番近いものを以下から選んでください。",
        "availableOptions": [
          "初めての症状である",
          "これまでに1回以上同じような症状があった",
          "年に数回程度は同じような症状がある",
          "月に数回程度は同じような症状がある",
          "ほぼ毎日同じような症状がある",
          "回答をとばす"
        ],
        "selectedOption": "初めての症状である",
        "timestamp": 1760682195084
      },
      {
        "questionNumber": 14,
        "url": "https://staging.ubie.app/qa/question/question-9892",
        "questionText": "【体の片側に感覚障害がある】の場所を教えてください",
        "availableOptions": [
          "手の指がしびれる",
          "手足以外のカラダにしびれがある",
          "顔や口周囲のしびれがある",
          "腕がしびれる",
          "お尻や腰回りにしびれがある",
          "足の付け根から足指のどこかにしびれがある",
          "この中に該当なし",
          "回答をとばす"
        ],
        "selectedOption": "手足以外のカラダにしびれがある",
        "timestamp": 1760682198228
      },
      {
        "questionNumber": 15,
        "url": "https://staging.ubie.app/qa/question/question-9994",
        "questionText": "【体の片側に感覚障害がある】の程度について、一番近いものを以下から選んでください。",
        "availableOptions": [
          "違和感がある",
          "やや耐えがたい",
          "とても耐えられない",
          "日常生活が困難である",
          "回答をとばす"
        ],
        "selectedOption": "回答をとばす",
        "timestamp": 1760682200496
      },
      {
        "questionNumber": 16,
        "url": "https://staging.ubie.app/qa/question/question-8326",
        "questionText": "【体の片側に感覚障害がある】はどのくらい続いていますか？",
        "availableOptions": [
          "15分以内",
          "1時間以内",
          "1時間以上続いている",
          "回答をとばす"
        ],
        "selectedOption": "1時間以内",
        "timestamp": 1760682203484
      },
      {
        "questionNumber": 17,
        "url": "https://staging.ubie.app/qa/question/question-7785",
        "questionText": "【体の片側に感覚障害がある】のはじまりから現在までの変化として、一番近いものはどれですか？",
        "availableOptions": [
          "悪化している",
          "改善も悪化もしていない",
          "改善したがまだ残っている",
          "改善し、現在はない",
          "回答をとばす"
        ],
        "selectedOption": "改善したがまだ残っている",
        "timestamp": 1760682205075
      },
      {
        "questionNumber": 18,
        "url": "https://staging.ubie.app/qa/question/question-9406",
        "questionText": "【体の片側に感覚障害がある】はどのような様子・状態ですか",
        "availableOptions": [
          "バランス感覚がおかしく、上手く立っていられない",
          "触ってないのにジンジン、ピリピリとしびれる感じがする",
          "この中に該当なし",
          "回答をとばす"
        ],
        "selectedOption": "回答をとばす",
        "timestamp": 1760682208289
      },
      {
        "questionNumber": 19,
        "url": "https://staging.ubie.app/qa/question/question-13602",
        "questionText": "一番最近の血液検査で、貧血を指摘されましたか？",
        "availableOptions": [
          "はい",
          "いいえ",
          "わからない",
          "回答をとばす"
        ],
        "selectedOption": "はい",
        "timestamp": 1760682209623
      },
      {
        "questionNumber": 20,
        "url": "https://staging.ubie.app/qa/question/question-15705",
        "questionText": "これまでにかかったことがある病気を【全て】選んでください",
        "availableOptions": [
          "気管支・肺の病気気管支喘息、慢性閉塞性肺疾患（COPD）、肺線維症・間質性肺炎",
          "リウマチ・膠原病関節リウマチ、全身性エリテマトーデス（SLE）、強皮症、多発性筋炎・皮膚筋炎、シェーグレン症候群",
          "アレルギー関連の病気アトピー性皮膚炎、気管支喘息、鼻茸（鼻ポリープ）、結節性痒疹、慢性閉塞性肺疾患（COPD）、慢性蕁麻疹、慢性副鼻腔炎、アレルギー性鼻炎、食物アレルギー",
          "生活習慣病・貧血糖尿病、脂質異常症、脂肪肝、貧血、高血圧",
          "皮ふの病気乾癬、アトピー性皮膚炎、慢性蕁麻疹、結節性痒疹",
          "腎臓の病気慢性腎臓病・慢性腎不全",
          "胃腸の病気潰瘍性大腸炎、胃食道逆流症（GERD/逆流性食道炎）、クローン病、機能性ディスペプシア、便秘症、胃・十二指腸潰瘍",
          "心臓の病気心不全、心筋梗塞・不安定狭心症、不整脈",
          "精神科・心療内科の病気うつ病、注意欠如多動症（ADHD）、統合失調症、双極性感情障害（躁うつ病）",
          "がん肺がん、乳がん、食道がん、胃がん、大腸がん、子宮頸がん、膵臓がん、前立腺がん、肝臓がん、皮膚がん",
          "この中に該当なし",
          "回答をとばす"
        ],
        "selectedOption": "回答をとばす",
        "timestamp": 1760682211375
      },
      {
        "questionNumber": 21,
        "url": "https://staging.ubie.app/qa/question/question-15656",
        "questionText": "以下の【アレルギーに関連する病気】をお持ちですか？当てはまるものを【全て】選んでください。",
        "availableOptions": [
          "アトピー性皮膚炎",
          "気管支喘息",
          "鼻茸（鼻ポリープ）",
          "結節性痒疹",
          "慢性蕁麻疹（じんましん）",
          "COPD（慢性閉塞性肺疾患）",
          "この中に該当なし",
          "回答をとばす"
        ],
        "selectedOption": "結節性痒疹",
        "timestamp": 1760682212841
      },
      {
        "questionNumber": 22,
        "url": "https://staging.ubie.app/qa/question/question-15455",
        "questionText": "医師に腎臓（じんぞう）の機能の低下を指摘されたことがありますか？",
        "availableOptions": [
          "ある（慢性腎臓病と診断済み）",
          "ある（慢性腎臓病と診断されていない）",
          "ない",
          "ないが、健康診断の血液検査（クレアチニン、eGFR）や尿検査で異常を指摘されている",
          "回答をとばす"
        ],
        "selectedOption": "ないが、健康診断の血液検査（クレアチニン、eGFR）や尿検査で異常を指摘されている",
        "timestamp": 1760682215277
      },
      {
        "questionNumber": 23,
        "url": "https://staging.ubie.app/qa/question/symptom-1460",
        "questionText": "安静にしていると痛みを感じないが、立ち上がる、歩く、階段をのぼる等の動作をすることで痛みが出て来ますか？",
        "availableOptions": [
          "はい",
          "いいえ",
          "わからない",
          "回答をとばす"
        ],
        "selectedOption": "回答をとばす",
        "timestamp": 1760682217915
      },
      {
        "questionNumber": 24,
        "url": "https://staging.ubie.app/qa/question/symptom-1563",
        "questionText": "首の痛みやこわばりがありますか？",
        "availableOptions": [
          "はい",
          "いいえ",
          "わからない",
          "回答をとばす"
        ],
        "selectedOption": "わからない",
        "timestamp": 1760682219884
      },
      {
        "questionNumber": 25,
        "url": "https://staging.ubie.app/qa/question/symptom-2178",
        "questionText": "腕が痛みますか？",
        "availableOptions": [
          "はい",
          "いいえ",
          "わからない",
          "回答をとばす"
        ],
        "selectedOption": "いいえ",
        "timestamp": 1760682222411
      },
      {
        "questionNumber": 26,
        "url": "https://staging.ubie.app/qa/question/symptom-1696",
        "questionText": "周りから見て反応が悪い、あるいは表情が乏しい状態ですか？",
        "availableOptions": [
          "はい",
          "いいえ",
          "わからない",
          "回答をとばす"
        ],
        "selectedOption": "わからない",
        "timestamp": 1760682224270
      },
      {
        "questionNumber": 27,
        "url": "https://staging.ubie.app/qa/question/symptom-932",
        "questionText": "現在、精神的なストレスや肉体的な疲労を感じていますか？",
        "availableOptions": [
          "はい",
          "いいえ",
          "わからない",
          "回答をとばす"
        ],
        "selectedOption": "はい",
        "timestamp": 1760682225951
      },
      {
        "questionNumber": 28,
        "url": "https://staging.ubie.app/qa/question/symptom-9811",
        "questionText": "ほてり・のぼせがありますか？",
        "availableOptions": [
          "はい",
          "いいえ",
          "わからない",
          "回答をとばす"
        ],
        "selectedOption": "いいえ",
        "timestamp": 1760682228099
      },
      {
        "questionNumber": 29,
        "url": "https://staging.ubie.app/qa/question/symptom-53",
        "questionText": "最近、普段とは違うおかしな行動をしていましたか？または、周りの人におかしな行動をしていたと指摘されましたか？",
        "availableOptions": [
          "はい",
          "いいえ",
          "わからない",
          "回答をとばす"
        ],
        "selectedOption": "回答をとばす",
        "timestamp": 1760682229871
      },
      {
        "questionNumber": 30,
        "url": "https://staging.ubie.app/qa/question/continue-symptom-answer",
        "questionText": "ここまでの回答でおおよその結果を確認できます",
        "availableOptions": [
          "ここまでの回答で結果を見る",
          "このまま回答を続ける"
        ],
        "selectedOption": "ここまでの回答で結果を見る",
        "timestamp": 1760682231276
      },
      {
        "questionNumber": 31,
        "url": "https://staging.ubie.app/qa/question/predicted-disease-question",
        "questionText": "この中でかかったことがある病気をすべて選んでください",
        "availableOptions": [
          "てんかん",
          "頚椎症",
          "更年期障害",
          "甲状腺機能低下症",
          "レストレスレッグス症候群(restless legs症候群)",
          "高尿酸血症",
          "線維筋痛症",
          "関節リウマチ(類縁疾患も含む)",
          "多発性硬化症",
          "この中に該当なし",
          "回答をとばす"
        ],
        "selectedOption": "多発性硬化症",
        "timestamp": 1760682233503
      },
      {
        "questionNumber": 32,
        "url": "https://staging.ubie.app/qa/question/disease-under-treatment",
        "questionText": "この中に治療中、またはお薬を飲んでいる病気はありますか？",
        "availableOptions": [
          "多発性硬化症",
          "この中に該当なし"
        ],
        "selectedOption": "多発性硬化症",
        "timestamp": 1760682235523
      },
      {
        "questionNumber": 33,
        "url": "https://staging.ubie.app/qa/question/diagnosed-poorly-controlled-disease-138-visit-status",
        "questionText": "【多発性硬化症】の治療のため、病院に通っていますか？",
        "availableOptions": [
          "病院に通っている",
          "病院に通っていない",
          "回答をとばす"
        ],
        "selectedOption": "病院に通っている",
        "timestamp": 1760682237789
      },
      {
        "questionNumber": 34,
        "url": "https://staging.ubie.app/qa/question/diagnosed-poorly-controlled-disease-138-medical-institution-recollection",
        "questionText": "治療で通っている病院の名前を覚えていますか？",
        "availableOptions": [
          "覚えている",
          "覚えているが名前が思い出せない（調べればわかる）",
          "わからない・覚えていない",
          "回答をとばす"
        ],
        "selectedOption": "覚えているが名前が思い出せない（調べればわかる）",
        "timestamp": 1760682239127
      },
      {
        "questionNumber": 35,
        "url": "https://staging.ubie.app/qa/question/diagnosed-poorly-controlled-disease-138-medical-institution",
        "questionText": "いま治療している病院を教えてください",
        "availableOptions": [
          "医療法人社団　三遠メディメイツ　岐阜メイツ睡眠クリニック岐阜県岐阜市藪田南4-15-20",
          "医療法人　川中島Fメンタルクリニック長野県長野市川中島町今井字稲荷1478-2",
          "甲府メンズメディカルクリニック山梨県甲府市相生2-5-3-102",
          "一般財団法人　ザ・ブラフ・クリニック　ザ・ブラフ・メディカル&デンタル・クリニック・医科神奈川県横浜市中区山手町82",
          "B-leafメディカル内科小児科クリニック茨城県つくば市小野崎字北出戸446-1",
          "岐阜メンタルクリニック岐阜県岐阜市若宮町5-12　若宮ビル3F",
          "医療法人　松若会　TFメディカル嶋北内科脳神経外科クリニック山形県山形市嶋北3-1-11",
          "調布メンタルクリニック東京都調布市小島町2-45-21　千早ビル2F201",
          "不破医院岐阜県不破郡垂井町宮代1674-1",
          "不破医院岐阜県羽島市正木町不破一色258",
          "株式会社　不二越　不二越病院富山県富山市東石金町11-65",
          "医療法人社団　新光会　不知火病院福岡県大牟田市手鎌1800",
          "医療法人社団　協和会　滝不動病院千葉県船橋市南三咲4-13-1",
          "医療法人　藍生会　不動ヶ丘病院埼玉県加須市岡古井107",
          "医療法人　清澄会　不破ノ関病院岐阜県不破郡垂井町94-1",
          "社会福祉法人　不動園　不動園診療所京都府宇治市白川東山15",
          "医療法人　緑楓会　不破クリニック岐阜県岐阜市太郎丸北郷243-5",
          "不動堂クリニック千葉県山武郡九十九里町西野1782",
          "医療法人社団　新光会　不知火クリニック福岡県福岡市博多区博多駅前3-16-13　由布ビル4F",
          "不二製油株式会社　不二製油阪南診療所大阪府泉佐野市住吉町1　厚生館2F",
          "医療法人　松本クリニック　松本不二夫整形外科宮城県仙台市太白区大野田4-18-1",
          "株式会社　不二越　不二越東富山診療所富山県富山市米田町3-2-1",
          "高幡不動ヒカリ眼科東京都日野市高幡116-10　京王高幡SC　3F",
          "医療法人社団　東京ハートサミット　東京心臓不整脈病院東京都江戸川区平井3-25-17",
          "幕張不整脈クリニック千葉県千葉市花見川区幕張町6-93-1",
          "株式会社不二家　不二家秦野工場診療所神奈川県秦野市曽屋228",
          "E.肌クリニック不来方岩手県紫波郡矢巾町大字南矢幅第8地割244",
          "きそがわ不破クリニック愛知県一宮市木曽川町里小牧字寺東172",
          "医療法人社団　東仁会　高幡不動じんクリニック東京都日野市高幡318",
          "医療法人　格心会　晴明病院福岡県福岡市城南区七隈8-20-10",
          "医療法人　回春堂　有明医院佐賀県杵島郡白石町大字築切851",
          "五明医院兵庫県神戸市兵庫区塚本通2-2-1",
          "医療法人社団　明円医院北海道砂川市空知太東一条3-1-14",
          "医療法人財団　杏林会　東明病院愛媛県松山市東方町甲1026-1",
          "医療法人社団　せいゆう会　神明病院兵庫県明石市大久保町大窪2520",
          "医療法人　信和会　明和病院兵庫県西宮市上鳴尾町4-31",
          "社会医療法人　明生会　明生病院大阪府大阪市都島区東野田町2-4-8",
          "医療法人　健生会　明生病院熊本県熊本市北区大窪2-6-20",
          "医療法人　愛友会　明石病院京都府京都市下京区西七条南衣田町93",
          "医療法人　開明眼科愛媛県西予市宇和町卯之町5-252",
          "明愛眼科滋賀県東近江市八日市本町3-4",
          "明宝医院岐阜県郡上市明宝大谷318-5",
          "医療法人社団　明芳会　明芳病院兵庫県神戸市中央区神若通6-4-1",
          "医療法人社団　互仁会　港明眼科愛知県名古屋市港区港明2-3-2　ららぽーと名古屋みなとアクルス3F3020",
          "明渓醫院福島県白河市明戸98-2",
          "医療法人社団　明石医院兵庫県淡路市生穂1760-1",
          "明石医院大阪府堺市北区東三国ヶ丘町5丁2-17　SATOMOビル1F",
          "明石医院大阪府八尾市北本町2-12-23",
          "医療法人財団　同仁記念会　明和病院東京都千代田区神田須田町1-18",
          "安明医院大阪府泉北郡忠岡町忠岡南1-14-3",
          "医療法人　明石医院山形県山形市旅篭町1-9-22",
          "明石医院神奈川県藤沢市湘南台7-15-14",
          "医療法人　明石眼科大阪府大阪市平野区平野宮町1-6-1　メガロコーポヒラノ101",
          "医療法人社団　啓明眼科北海道札幌市中央区南十三条西21-3-18",
          "医療法人　明石医院大阪府豊中市庄内幸町3-18-21",
          "医療法人　日明会　日明病院福岡県北九州市小倉北区日明3-3-32",
          "医療法人　明治病院福島県福島市北町2-40",
          "医療法人　松仁会　明徳病院大阪府大阪市旭区生江1-3-26",
          "光明醫院静岡県菊川市富田2593",
          "医療法人　十全会　聖明病院静岡県富士市大渕888",
          "医療法人社団　弘成会　明海病院兵庫県明石市藤江201",
          "さっぽろ不整脈クリニック北海道札幌市中央区大通西6-10-10　大通公園ビル3F",
          "一般財団法人　仁明会　仁明会病院兵庫県西宮市甲山町53-20",
          "医療法人社団　明星会　明星診療所岐阜県加茂郡富加町夕田380",
          "社会福祉法人　天恵会　有明診療所熊本県玉名市天水町部田見440",
          "医療法人　十全会　早明浦病院高知県土佐郡土佐町田井1372",
          "光明診療所茨城県結城市上山川2035-3",
          "明日香医院東京都杉並区高井戸西2-16-29",
          "ジャパンマリンユナイテッド株式会社　有明診療所熊本県玉名郡長洲町有明1",
          "古明地医院東京都豊島区南長崎1-16-17",
          "眼科好明館岐阜県岐阜市長良157-1",
          "医療法人社団　大佑会　明育小児科東京都江戸川区東葛西2-3-16",
          "医療法人社団　自明堂医院　自明堂眼科新潟県長岡市殿町3-2-8",
          "弘明寺内科神奈川県横浜市南区大岡2-1-17　セレサ弘明寺101",
          "医療法人社団　康明会　康明会病院東京都日野市豊田2-32-1",
          "眼科明眼院愛知県名古屋市中川区大畑町2-14-1　コーポ奈津1F",
          "明星会医院東京都青梅市上町362-1　青梅ガーデンヒルズPART3-1F",
          "医療法人　玉光会　豊明栄病院愛知県豊明市栄町大根1-395",
          "社会医療法人　垣谷会　明治橋病院大阪府松原市三宅西1-358-3",
          "不動前レディースクリニック東京都品川区西五反田5-11-13",
          "学校法人　明海大学　明海大学歯学部付属　明海大学病院埼玉県坂戸市けやき台1-1",
          "医療法人　晴明会　糸満晴明病院沖縄県糸満市大度520",
          "医療法人社団　聖和会　有明成仁病院熊本県玉名郡長洲町宮野2775",
          "医療法人　明仁会　明舞中央病院兵庫県明石市松が丘4-1-32",
          "社会福祉法人　明芳会　明芳会診療所熊本県熊本市東区長嶺南4-12-65",
          "社会医療法人　明生会　明生第二病院大阪府大阪市東成区東小橋1-19-20",
          "医療法人　若宮会　菅海明堂医院熊本県玉名市大浜町735",
          "医療法人　明穂整形外科鳥取県鳥取市扇町11-3",
          "医療法人　久仁会　明石同仁病院兵庫県明石市魚住町清水2183",
          "明治河野医院大分県大分市大字横尾3937-8",
          "医療法人社団　正仁会　明石土山病院兵庫県明石市魚住町清水2744-30",
          "医療法人　若葉会　明石回生病院兵庫県明石市二見町東二見549-1",
          "医療法人　ライフサポート　明和記念病院大分県大分市明野北1-2-17",
          "医療法人　公仁会　明石仁十病院兵庫県明石市魚住町清水1871-3",
          "孝明舘診療所長野県安曇野市明科七貴3681",
          "医療法人財団　老蘇会　静明館診療所北海道札幌市中央区南十四条西18-5-33",
          "神明整形外科千葉県千葉市中央区神明町33-7",
          "医療法人　茗悠会　明野中央医院茨城県筑西市海老ケ島926",
          "社会医療法人　豊生会　丘珠明陽医院北海道札幌市東区北丘珠三条1-21-20",
          "明徳漢方内科京都府京都市下京区七条通新町東入西境町163　京都駅前増井ビル5F",
          "社会福祉法人　明照会　明照会診療所兵庫県伊丹市中野西1-18",
          "医療法人　明寿会　明石内科医院福岡県福岡市城南区鳥飼5-19-12",
          "社会福祉法人　清志会　紫明寮診療所熊本県天草市五和町二江4668",
          "医療法人社団　唱和会　明野中央病院大分県大分市明野東2-7-33",
          "医療法人社団　明治眼科医院北海道小樽市稲穂2-7-17",
          "明園内科医院北海道札幌市東区北二十三条東13-1-15",
          "医療法人　光熙会　明治記念医院福岡県飯塚市川津360-3",
          "医療法人社団　明生会　三橋明生病院千葉県千葉市中央区亀井町2-3",
          "医療法人社団　明生会　都城明生病院宮崎県都城市金田町2263",
          "医療法人社団　ホームアレー　ホームアレークリニック不動前東京都品川区西五反田3-15-8　Biz-Field9F",
          "泌尿器と男性不妊のクリニック埼玉県さいたま市大宮区大門町2-118",
          "株式会社不二家　株式会社不二家平塚工場診療所神奈川県平塚市西八幡1-4-1",
          "医療法人社団　モルゲンロート　有明みんなクリニック有明ガーデン院東京都江東区有明2-1-7　有明ガーデン1F",
          "深沢不動なかむら脳神経外科内科東京都世田谷区深沢4-34-7",
          "社会福祉法人　大阪暁明館　大阪暁明館病院大阪府大阪市此花区西九条5-4-8",
          "復明館　水谷眼科愛知県西尾市丁田町落1",
          "医療法人　明峰会　明峰クリニック福井県敦賀市津内町3-6-38",
          "明大前肛門医院東京都世田谷区松原1-31-21",
          "社会福祉法人　水俣市社会福祉事業団　水俣市立明水園熊本県水俣市浜4076",
          "医療法人社団　翔嶺館　音更宏明館病院北海道河東郡音更町木野大通東17-1-6",
          "源明クリニック東京都品川区二葉3-1-16",
          "弘明クリニック神奈川県横浜市南区通町4-84-1　メルベイユ弘明寺2F",
          "社会医療法人　明陽会　明陽クリニック愛知県豊橋市八通町64-3　老健施設ビル内6F",
          "医療法人社団　高邦会　有明クリニック福岡県大川市大字酒見215-1",
          "明石クリニック大阪府豊中市玉井町1-2-1　豊中駅前ビル4F",
          "明陽クリニック愛知県名古屋市北区長喜町2-33-2",
          "医療法人　健友会　弘明寺清水眼科神奈川県横浜市南区六ツ川1-70-9",
          "医療法人　開明クリニック愛知県一宮市開明字郷東39",
          "明元堂眼科医院新潟県新潟市中央区上大川前通9番町1279",
          "医療法人社団　明日佳　桜台明日佳病院北海道札幌市厚別区厚別西五条5-1-1",
          "医療法人社団　新明外科胃腸科神奈川県横須賀市金谷2-2-15",
          "虫明クリニック東京都町田市金森3-19-11",
          "学校法人　明治大学　明治大学診療所東京都千代田区神田駿河台1-3-1",
          "明陵クリニック神奈川県大和市渋谷7-1-8-101",
          "復明堂眼科医院青森県五所川原市字旭町65",
          "医療法人社団　唯円会　啓明クリニック北海道札幌市中央区南十三条西22-2-3",
          "医療法人　高山内科明生会長野県松本市島内1788-2",
          "明徳クリニック愛知県名古屋市名東区猪子石3-1214-1",
          "医療法人　豊明クリニック愛知県豊明市新栄町2-133",
          "公益財団法人　がん研究会　がん研有明病院東京都江東区有明3-8-31",
          "医療法人社団　明日佳　札幌明日佳病院北海道札幌市中央区宮の森一条17-1-25",
          "明神クリニック宮城県仙台市青葉区中央2-6-36　レントビル6F",
          "医療法人社団　せいゆう会　神明クリニック兵庫県明石市大久保町ゆりのき通2-2-4　INUIゆりのき通ビル4F",
          "明海クリニック千葉県山武市蓮沼イ1372-2",
          "明石クリニック岐阜県瑞穂市馬場上光町1-106",
          "学校法人　明星学苑　明星大学診療所東京都日野市程久保2-1-1",
          "医療法人社団　養明堂眼科医院埼玉県さいたま市大宮区宮町2-9",
          "有明台整形外科新潟県新潟市中央区堀割町2-6",
          "医療法人社団　明石台整形外科宮城県富谷市明石台2-22-5",
          "明石クリニック兵庫県尼崎市塚口町6-18-11",
          "豊明ぜんご眼科愛知県豊明市間米町島川2155-2",
          "医療法人　白水会　明陽クリニック沖縄県沖縄市園田1-4-5",
          "医療法人　涼風会　明誠クリニック愛知県稲沢市日下部南町1-1-1",
          "医療法人社団　明日佳　白石明日佳病院北海道札幌市白石区東札幌五条5-2-5",
          "医療法人　明星会　明星クリニック愛媛県松山市井門町462-1",
          "医療法人　明生会　明生クリニック岐阜県瑞浪市北小田町2-198",
          "明神クリニック福岡県福岡市中央区大手門3-8-20　ラ・コミューン大手門702",
          "医療法人社団　明日佳　宮の沢明日佳病院北海道札幌市西区西町南20-1-30",
          "医療法人　明石整形外科医院山口県周南市慶万町1-15",
          "医療法人　灯里　明日花クリニック福岡県福津市日蒔野3-1-109",
          "医療法人社団　憲幸会　有明ガーデン眼科東京都江東区有明2-1-8　有明ガーデン4F",
          "医療法人　杏林堂　明島整形外科医院長崎県南島原市布津町乙1859-2",
          "社会福祉法人　聖明福祉協会　聖明園寿荘診療所東京都青梅市根ケ布2-724",
          "医療法人社団　福聚会　神明台クリニック東京都羽村市神明台1-35-4",
          "一般財団法人　仁明会　仁明会クリニック兵庫県西宮市越水町4-31",
          "社会福祉法人　愛知県厚生事業団　愛厚明知寮診療所愛知県春日井市明知町420",
          "社会福祉法人　宇治明星園　宇治明星園診療所京都府宇治市莵道岡谷16-3",
          "社会医療法人　明生会　明生会クリニック大阪府大阪市西成区太子2-2-18　タイシ第一ビル",
          "社会医療法人　愛仁会　明石医療センター兵庫県明石市大久保町八木743-33",
          "明大前クリニック東京都世田谷区松原2-42-14　美鈴Sビル1F",
          "明和整形外科醫院大分県大分市大字毛井字寺の前279-3",
          "医療法人　平明会　平明会クリニック兵庫県三田市福島66-4",
          "熊本県有明保健所熊本県玉名市岩崎1004-1",
          "社会福祉法人　清明会　清明会本部診療所東京都八王子市裏高尾町957",
          "医療法人　明正会　明正会クリニック京都府京都市西京区桂南巽町146　グランシューズ桂2F",
          "医療法人　明輝会　明輝会クリニック鹿児島県鹿児島市川上町2750-18",
          "医療法人社団　橘医会　西明石クリニック兵庫県明石市西明石南町2-10-5",
          "一般財団法人　杏仁会　くまもと青明病院熊本県熊本市中央区渡鹿5-1-37",
          "地方独立行政法人　明石市立市民病院兵庫県明石市鷹匠町1-33",
          "社会医療法人　祥和会　明神館クリニック広島県福山市明神町2-5-22",
          "社会医療法人　共愛会　明治町クリニック福岡県北九州市戸畑区明治町10-18",
          "医療法人社団　明日佳　岩見沢明日佳病院北海道岩見沢市志文町297-13",
          "明石Mクリニック大分県別府市御幸9組",
          "社会福祉法人　明石愛老園　明石愛老園診療所兵庫県明石市魚住町清水3208",
          "医療法人　明神会　明神台クリニック神奈川県横浜市保土ケ谷区明神台1-9　コンフォール明神台団地第1街区第9棟",
          "百合ヶ丘つだ内科心臓不整脈クリニック神奈川県川崎市麻生区百合丘1-1-1　クリエイト・ゆりストア3F",
          "医療法人財団　明理会　明理会中央総合病院東京都北区東十条3-2-11",
          "黎明脳神経外科医院鹿児島県鹿屋市串良町上小原字武左ヱ門迫3500-1",
          "医療法人　明瞳会　明瞳眼科クリニック群馬県富岡市富岡1112",
          "明治ホールディングス株式会社　明治京橋ビル診療所東京都中央区京橋2-4-16　明治京橋ビル11F",
          "神明通りクリニック東京都杉並区宮前3-25-13　メゾンフラワー",
          "明石いしだ形成外科兵庫県明石市西新町3-13-40",
          "医療法人　明石内科クリニック広島県廿日市市山陽園8-19　ステイツ野村1F",
          "医療法人社団　為成会　明治通りクリニック東京都渋谷区神南1-11-1　渋谷市野ビル4F",
          "医療法人社団　ひとみ会　回明堂眼科・歯科・医科北海道札幌市豊平区月寒中央通10-5-11",
          "学校法人　明治大学　明治大学中野診療所東京都中野区中野4-21-1",
          "太田明々堂眼科医院東京都文京区本郷1-33-12　本郷壱岐坂ハイツ103号室",
          "医療法人社団　坂本眼科　明生アイクリニック兵庫県神戸市中央区北長狭通1-2-2　エビスナカジマビル2F",
          "医療法人社団　晃和会　半明内科クリニック広島県廿日市市宮内4-10-23",
          "泰明小前クリニック東京都中央区銀座6-2-3　Daiwa銀座アネックス4F",
          "回答をとばす"
        ],
        "selectedOption": "幕張不整脈クリニック千葉県千葉市花見川区幕張町6-93-1",
        "timestamp": 1760682241949
      },
      {
        "questionNumber": 36,
        "url": "https://staging.ubie.app/qa/question/symptom-care-needs",
        "questionText": "今回、【体の片側に感覚障害がある】についてどのような対応をしたいですか？",
        "availableOptions": [
          "市販薬で対処したい",
          "医師に診てもらいたい",
          "症状に関する病気を詳しく知りたい",
          "該当するものがない",
          "回答をとばす"
        ],
        "selectedOption": "市販薬で対処したい",
        "timestamp": 1760682243476
      }
    ]
  },
  "differences": {
    "diseaseMismatch": {
      "cDiagnosisOnly": [
        {
          "id": "脊髄損傷急性期",
          "name": "脊髄損傷急性期",
          "section": "related"
        },
        {
          "id": "神経障害性疼痛",
          "name": "神経障害性疼痛",
          "section": "related"
        },
        {
          "id": "梨状筋症候群",
          "name": "梨状筋症候群",
          "section": "related"
        },
        {
          "id": "変形性腰椎症",
          "name": "変形性腰椎症",
          "section": "related"
        },
        {
          "id": "頚髄損傷",
          "name": "頚髄損傷",
          "section": "related"
        },
        {
          "id": "視神経脊髄炎",
          "name": "視神経脊髄炎",
          "label": "指定難病",
          "section": "easily-missed"
        }
      ],
      "askmanOnly": [
        {
          "id": "甲状腺機能低下症",
          "name": "甲状腺機能低下症",
          "section": "related"
        },
        {
          "id": "レストレスレッグス症候群(むずむず脚症候群)",
          "name": "レストレスレッグス症候群(むずむず脚症候群)",
          "section": "related"
        },
        {
          "id": "高尿酸血症",
          "name": "高尿酸血症",
          "section": "related"
        },
        {
          "id": "線維筋痛症",
          "name": "線維筋痛症",
          "section": "related"
        },
        {
          "id": "関節リウマチ",
          "name": "関節リウマチ",
          "label": "指定難病と関連あり",
          "section": "related"
        },
        {
          "id": "一過性脳虚血発作",
          "name": "一過性脳虚血発作",
          "section": "easily-missed"
        }
      ]
    },
    "questionCountMismatch": {
      "cDiagnosis": 38,
      "askman": 36
    }
  }
}